forgejo_ntfy/__init__.py
forgejo_ntfy/_version.py
forgejo_ntfy-0.1.0.dist-info/METADATA
forgejo_ntfy-0.1.0.dist-info/WHEEL
forgejo_ntfy-0.1.0.dist-info/entry_points.txt
forgejo_ntfy-0.1.0.dist-info/licenses/LICENSE
forgejo_ntfy-0.1.0.dist-info/RECORD
