Metadata-Version: 2.4
Name: forgejo-ntfy
Version: 0.1.0
Summary: feed Forgejo notifications to ntfy.sh
Project-URL: Homepage, https://codeberg.org/mih/forgejo-ntfy
Project-URL: Documentation, https://codeberg.org/mih/forgejo-ntfy#readme
Project-URL: Issues, https://codeberg.org/mih/forgejo-ntfy/issues
Project-URL: Source, https://codeberg.org/mih/forgejo-ntfy
Project-URL: Changelog, https://codeberg.org/mih/forgejo-ntfy/src/branch/main/CHANGELOG.md
Author-email: Michael Hanke <mih@ngln.eu>
Maintainer-email: Michael Hanke <mih@ngln.eu>
License-Expression: MIT
License-File: LICENSE
Keywords: forgejo,notifications,ntfy
Classifier: Development Status :: 4 - Beta
Classifier: Intended Audience :: Developers
Classifier: Intended Audience :: End Users/Desktop
Classifier: License :: OSI Approved :: MIT License
Classifier: Natural Language :: English
Classifier: Operating System :: OS Independent
Classifier: Programming Language :: Python
Classifier: Programming Language :: Python :: 3
Classifier: Programming Language :: Python :: 3.11
Classifier: Programming Language :: Python :: 3.12
Classifier: Programming Language :: Python :: 3.13
Classifier: Programming Language :: Python :: 3.14
Classifier: Programming Language :: Python :: Implementation :: CPython
Classifier: Programming Language :: Python :: Implementation :: PyPy
Classifier: Topic :: Software Development
Requires-Python: >=3.11
Requires-Dist: httpx
Requires-Dist: humanize
